aiohttp_oauth/__init__.py
aiohttp_oauth/auth.py
aiohttp_oauth/dummy.py
aiohttp_oauth/github.py
aiohttp_oauth/google.py
aiohttp_oauth/gsuite.py
aiohttp_oauth-0.7.0.dist-info/DESCRIPTION.rst
aiohttp_oauth-0.7.0.dist-info/METADATA
aiohttp_oauth-0.7.0.dist-info/RECORD
aiohttp_oauth-0.7.0.dist-info/WHEEL
aiohttp_oauth-0.7.0.dist-info/metadata.json
aiohttp_oauth-0.7.0.dist-info/top_level.txt
