Metadata-Version: 2.0
Name: aiohttp-oauth
Version: 0.7.0
Summary: oauth middleware for aiohttp
Home-page: https://github.com/CanopyTax/aiohttp-oauth
Author: nhumrich
Author-email: nick@humrich.us
License: Apache
Platform: UNKNOWN
Classifier: Development Status :: 4 - Beta
Classifier: Intended Audience :: Developers
Classifier: Natural Language :: English
Classifier: Programming Language :: Python
Classifier: Programming Language :: Python :: 3.5
Requires-Dist: aioauth-client
Requires-Dist: aiohttp
Requires-Dist: aiohttp-session
Requires-Dist: cryptography
